sarf_simple_crud/__init__.py
sarf_simple_crud/simple_crud.py
sarf_simple_crud/dal/__init__.py
sarf_simple_crud/dal/base.py
sarf_simple_crud/dal/infra/__init__.py
sarf_simple_crud/dal/infra/json_dal.py
sarf_simple_crud/test/__init__.py
sarf_simple_crud/test/conftest.py
sarf_simple_crud/test/dummy_class.py
sarf_simple_crud/test/simple_crud_test.py
simple_crud/__init__.py
simple_crud/simple_crud.py
simple_crud/dal/__init__.py
simple_crud/dal/base.py
simple_crud/dal/infra/__init__.py
simple_crud/dal/infra/json_dal.py
simple_crud/test/__init__.py
simple_crud/test/conftest.py
simple_crud/test/dummy_class.py
simple_crud/test/simple_crud_test.py
simplecrud/__init__.py
simplecrud/simple_crud.py
simplecrud/dal/__init__.py
simplecrud/dal/base.py
simplecrud/dal/infra/__init__.py
simplecrud/dal/infra/json_dal.py
simplecrud/test/__init__.py
simplecrud/test/conftest.py
simplecrud/test/dummy_class.py
simplecrud/test/simple_crud_test.py
sarf_simple_crud-0.1.0.dist-info/METADATA
sarf_simple_crud-0.1.0.dist-info/WHEEL
sarf_simple_crud-0.1.0.dist-info/top_level.txt
sarf_simple_crud-0.1.0.dist-info/RECORD
