Metadata-Version: 2.1
Name: sarf-simple-crud
Version: 0.1.0
Summary: An extremely simple and basic interface for creating CRUD apps with an example of implementation using a JSON database.
Home-page: UNKNOWN
Author: Samuel López Saura
Author-email: samuellopezsaura@gmail.com
License: MIT
Platform: UNKNOWN
Classifier: Programming Language :: Python :: 3
Classifier: License :: OSI Approved :: MIT License
Classifier: Operating System :: OS Independent
